pyautogui-stubs/METADATA.toml
pyautogui-stubs/__init__.pyi
pyautogui-stubs/py.typed
types_PyAutoGUI-0.9.3.20240406.dist-info/METADATA
types_PyAutoGUI-0.9.3.20240406.dist-info/WHEEL
types_PyAutoGUI-0.9.3.20240406.dist-info/top_level.txt
types_PyAutoGUI-0.9.3.20240406.dist-info/RECORD
